dayplot/__init__.py
dayplot/calendar.py
dayplot/github.py
dayplot/sample.csv
dayplot/styles.py
dayplot/utils.py
dayplot-0.4.2.dist-info/licenses/LICENSE
dayplot-0.4.2.dist-info/METADATA
dayplot-0.4.2.dist-info/WHEEL
dayplot-0.4.2.dist-info/top_level.txt
dayplot-0.4.2.dist-info/RECORD
