Metadata-Version: 2.4
Name: dayplot
Version: 0.4.2
Summary: Calendar heatmaps with matplotlib
Author-email: Joseph Barbier <joseph.barbierdarnal@gmail.com>
License-Expression: MIT
Project-URL: Homepage, https://y-sunflower.github.io/dayplot/
Project-URL: Issues, https://github.com/y-sunflower/dayplot/issues
Project-URL: Documentation, https://y-sunflower.github.io/dayplot/reference/calendar/
Project-URL: Repository, https://github.com/y-sunflower/dayplot
Keywords: matplotlib,calendar,heatmap,github,plot
Requires-Python: >=3.9
License-File: LICENSE
Requires-Dist: matplotlib
Requires-Dist: narwhals>=1.0.0
Provides-Extra: data
Requires-Dist: requests; extra == "data"
Dynamic: license-file
